Workbook

Sheet Movies_data
A1: Movie_ID | B1: Movie_Name | C1: Language | D1: Genre | E1: Release_Date | F1: Duration_Minutes | G1: Certification | H1: Rating | I1: Director | J1: Production_House | L1: Movie_id
A2: M001 | B2: Leo | C2: Tamil | D2: Action | E2: 45218 | F2: 164 | G2: UA | H2: 8 | I2: Lokesh Kanagaraj | J2: Lyca Productions | L2: =COUNTIF(A2:A45,A2) -> 1
A3: M002 | B3: Jailer | C3: Tamil | D3: Action | E3: 45148 | F3: 168 | G3: UA | H3: 7.1 | I3: Nelson Dilipkumar | J3: Sun Pictures | L3: =COUNTIF(A3:A46,A3) -> 1
A4: M003 | B4: Vikram | C4: Tamil | D4: Action | E4: 44715 | F4: 175 | G4: UA | H4: 8.3 | I4: Lokesh Kanagaraj | J4: T-Series | L4: =COUNTIF(A4:A47,A4) -> 1
A5: M004 | B5: Ponniyin Selvan I | C5: Tamil | D5: Drama | E5: 44834 | F5: 167 | G5: UA | H5: 7.6 | I5: Mani Ratnam | J5: Mythri Movie Makers | L5: =COUNTIF(A5:A48,A5) -> 1
A6: M005 | B6: Ponniyin Selvan II | C6: Tamil | D6: Drama | E6: 45044 | F6: 164 | G6: UA | H6: 7.3 | I6: Mani Ratnam | J6: Mythri Movie Makers | L6: =COUNTIF(A6:A49,A6) -> 1
A7: M006 | B7: Maamannan | C7: Tamil | D7: Drama | E7: 45106 | F7: 155 | G7: UA | H7: 7.3 | I7: Mari Selvaraj | J7: Hombale Films | L7: =COUNTIF(A7:A50,A7) -> 1
A8: M007 | B8: Good Night | C8: Tamil | D8: Comedy | E8: 45058 | F8: 142 | G8: UA | H8: 8 | I8: Vinayak Chandrasekaran | J8: Lyca Productions | L8: =COUNTIF(A8:A51,A8) -> 1
A9: M008 | B9: Love Today | C9: Tamil | D9: Romance | E9: 44869 | F9: 154 | G9: U/A | H9: 7.4 | I9: Pradeep Ranganathan | J9: Red Giant Movies | L9: =COUNTIF(A9:A52,A9) -> 1
A10: M009 | B10: Amaran | C10: Tamil | D10: Biography | E10: 45596 | F10: 169 | G10: UA | H10: 8.3 | I10: Rajkumar Periasamy | J10: Lyca Productions | L10: =COUNTIF(A10:A53,A10) -> 1
A11: M010 | B11: Captain Miller | C11: Tamil | D11: Action | E11: 45303 | F11: 157 | G11: UA | H11: 7 | I11: Arun Matheswaran | J11: Dream Warrior Pictures | L11: =COUNTIF(A11:A54,A11) -> 1
A12: M011 | B12: Pushpa 2 | C12: Telugu | D12: Action | E12: 45631 | F12: 200 | G12: UA | H12: 6.1 | I12: Sukumar | J12: Geetha Arts | L12: =COUNTIF(A12:A55,A12) -> 1
A13: M012 | B13: RRR | C13: Telugu | D13: Action | E13: 44645 | F13: 182 | G13: UA | H13: 7.8 | I13: S. S. Rajamouli | J13: Sun Pictures | L13: =COUNTIF(A13:A56,A13) -> 1
... A41: M040 | B41: Inside Out 2 | C41: English | D41: Animation | E41: 45457 | F41: 96 | G41: U | H41: 7.6 | I41: Kelsey Mann | J41: Dharma Productions | L41: =COUNTIF(A41:A84,A41) -> 1

Sheet Booking_data
A1: Booking_ID | B1: Booking_Date | C1: Show_Date | D1: Movie_ID | E1: Cinema_ID | F1: Show_Time | G1: Screen | H1: Tickets | I1: Ticket_Price | J1: Convenience_Fee | K1: Discount | L1: Payment_Mode | M1: Booking_Status | N1: Customer_Age | O1: Customer_Gender | P1: Booking_Channel | Q1: Format
A2: B000001 | B2: 46139 | C2: 46139 | D2: M038 | E2: C162 | F2: 0.9375 | G2: 5 | H2: 6 | I2: 160 | J2: 54 | K2: 60 | L2: Wallet | M2: Confirmed | N2: 24 | O2: Other | P2: Mobile App | Q2: 2D
A3: B000002 | B3: 46062 | C3: 46067 | D3: M029 | E3: C122 | F3: 0.64583333 | G3: 7 | H3: 5 | I3: 360 | J3: 48 | K3: 20 | L3: Debit Card | M3: Confirmed | N3: 25 | O3: Male | P3: Mobile App | Q3: IMAX
A4: B000003 | B4: 46084 | C4: 46085 | D4: M003 | E4: C112 | F4: 0.77083333 | G4: 9 | H4: 6 | I4: 240 | J4: 54 | K4: 20 | L4: Credit Card | M4: Confirmed | N4: 60 | O4: Female | P4: Website | Q4: 2D
A5: B000004 | B5: 46077 | C5: 46080 | D5: M026 | E5: C092 | F5: 0.39583333 | G5: 3 | H5: 3 | I5: 160 | J5: 36 | K5: 20 | L5: UPI | M5: Confirmed | N5: 32 | O5: Other | P5: Mobile App | Q5: 2D
A6: B000005 | B6: 46173 | C6: 46176 | D6: M001 | E6: C161 | F6: 0.88541667 | G6: 4 | H6: 2 | I6: 280 | J6: 30 | K6: 100 | L6: Debit Card | M6: Confirmed | N6: 22 | O6: Other | P6: Website | Q6: 2D
A7: B000006 | B7: 46077 | C7: 46079 | D7: M027 | E7: C131 | F7: 0.39583333 | G7: 1 | H7: 3 | I7: 340 | J7: 36 | K7: 60 | L7: Net Banking | M7: Confirmed | N7: 30 | O7: Female | P7: Website | Q7: IMAX
A8: B000007 | B8: 46128 | C8: 46135 | D8: M034 | E8: C021 | F8: 0.53125 | G8: 2 | H8: 1 | I8: 220 | J8: 24 | K8: 40 | L8: Credit Card | M8: Confirmed | N8: 24 | O8: Other | P8: Website | Q8: 2D
A9: B000008 | B9: 46058 | C9: 46064 | D9: M005 | E9: C103 | F9: 0.39583333 | G9: 1 | H9: 5 | I9: 180 | J9: 48 | K9: 0 | L9: Wallet | M9: Confirmed | N9: 53 | O9: Male | P9: Mobile App | Q9: 2D
A10: B000009 | B10: 46083 | C10: 46085 | D10: M011 | E10: C111 | F10: 0.77083333 | G10: 3 | H10: 5 | I10: 180 | J10: 48 | K10: 100 | L10: Net Banking | M10: Confirmed | N10: 18 | O10: Female | P10: Website | Q10: 2D
A11: B000010 | B11: 46201 | C11: 46208 | D11: M004 | E11: C071 | F11: 0.39583333 | G11: 1 | H11: 6 | I11: 180 | J11: 54 | K11: 20 | L11: Wallet | M11: Confirmed | N11: 38 | O11: Female | P11: Mobile App | Q11: 2D
A12: B000011 | B12: 46037 | C12: 46038 | D12: M033 | E12: C022 | F12: 0.53125 | G12: 1 | H12: 1 | I12: 380 | J12: 24 | K12: 100 | L12: Wallet | M12: Confirmed | N12: 54 | O12: Male | P12: Website | Q12: IMAX
A13: B000012 | B13: 46191 | C13: 46196 | D13: M037 | E13: C052 | F13: 0.77083333 | G13: 3 | H13: 2 | I13: 200 | J13: 30 | K13: 0 | L13: UPI | M13: Confirmed | N13: 37 | O13: Male | P13: Website | Q13: 2D
... A6001: B006000 | B6001: 46079 | C6001: 46081 | D6001: M007 | E6001: C072 | F6001: 0.77083333 | G6001: 7 | H6001: 3 | I6001: 380 | J6001: 36 | K6001: 60 | L6001: UPI | M6001: Confirmed | N6001: 33 | O6001: Other | P6001: Mobile App | Q6001: IMAX

Sheet Cinemas_data
A1: Cinema_ID | B1: Cinema_Name | C1: City | D1: State | E1: Cinema_Type | F1: Screens | G1: Total_Seats | H1: Base_Ticket_Price | I1: Cinema_name
A2: C011 | B2: Cinepolis City Centre, Chennai | C2: Chennai | D2: Tamil Nadu | E2: Multiplex | F2: 10 | G2: 1520 | H2: 240 | I2: =_xlfn.TEXTBEFORE(B2,",") -> Cinepolis City Centre
A3: C012 | B3: Miraj Cinemas Grand Mall, Chennai | C3: Chennai | D3: Tamil Nadu | E3: Multiplex | F3: 6 | G3: 1086 | H3: 160 | I3: =_xlfn.TEXTBEFORE(B3,",") -> Miraj Cinemas Grand Mall
A4: C013 | B4: Mukta A2 Cinemas Forum Mall, Chennai | C4: Chennai | D4: Tamil Nadu | E4: Multiplex | F4: 9 | G4: 1431 | H4: 240 | I4: =_xlfn.TEXTBEFORE(B4,",") -> Mukta A2 Cinemas Forum Mall
A5: C021 | B5: Miraj Cinemas City Centre, Coimbatore | C5: Coimbatore | D5: Tamil Nadu | E5: Multiplex | F5: 4 | G5: 756 | H5: 220 | I5: =_xlfn.TEXTBEFORE(B5,",") -> Miraj Cinemas City Centre
A6: C022 | B6: Mukta A2 Cinemas Grand Mall, Coimbatore | C6: Coimbatore | D6: Tamil Nadu | E6: Multiplex | F6: 4 | G6: 660 | H6: 200 | I6: =_xlfn.TEXTBEFORE(B6,",") -> Mukta A2 Cinemas Grand Mall
A7: C023 | B7: MovieMax Forum Mall, Coimbatore | C7: Coimbatore | D7: Tamil Nadu | E7: Multiplex | F7: 10 | G7: 1700 | H7: 240 | I7: =_xlfn.TEXTBEFORE(B7,",") -> MovieMax Forum Mall
A8: C031 | B8: Mukta A2 Cinemas City Centre, Madurai | C8: Madurai | D8: Tamil Nadu | E8: Multiplex | F8: 10 | G8: 1530 | H8: 240 | I8: =_xlfn.TEXTBEFORE(B8,",") -> Mukta A2 Cinemas City Centre
A9: C032 | B9: MovieMax Grand Mall, Madurai | C9: Madurai | D9: Tamil Nadu | E9: Multiplex | F9: 5 | G9: 875 | H9: 160 | I9: =_xlfn.TEXTBEFORE(B9,",") -> MovieMax Grand Mall
A10: C033 | B10: Asian Cinemas Forum Mall, Madurai | C10: Madurai | D10: Tamil Nadu | E10: Multiplex | F10: 4 | G10: 688 | H10: 180 | I10: =_xlfn.TEXTBEFORE(B10,",") -> Asian Cinemas Forum Mall
A11: C041 | B11: MovieMax City Centre, Salem | C11: Salem | D11: Tamil Nadu | E11: Multiplex | F11: 10 | G11: 1480 | H11: 160 | I11: =_xlfn.TEXTBEFORE(B11,",") -> MovieMax City Centre
A12: C042 | B12: Asian Cinemas Grand Mall, Salem | C12: Salem | D12: Tamil Nadu | E12: Multiplex | F12: 10 | G12: 1440 | H12: 280 | I12: =_xlfn.TEXTBEFORE(B12,",") -> Asian Cinemas Grand Mall
A13: C043 | B13: City Pride Forum Mall, Salem | C13: Salem | D13: Tamil Nadu | E13: Multiplex | F13: 4 | G13: 616 | H13: 200 | I13: =_xlfn.TEXTBEFORE(B13,",") -> City Pride Forum Mall
... A49: C163 | B49: Miraj Cinemas Forum Mall, Thiruvananthapuram | C49: Thiruvananthapuram | D49: Kerala | E49: Multiplex | F49: 6 | G49: 942 | H49: 180 | I49: =_xlfn.TEXTBEFORE(B49,",") -> Miraj Cinemas Forum Mall

Sheet Theatre_Analysis
A2: Therate Revenue Analysis
A3: Therate Name | B3: Revenue
A4: Asian Cinemas City Centre | B4: 219540
A5: Asian Cinemas Forum Mall | B5: 185780
A6: Asian Cinemas Grand Mall | B6: 204800 | D6: Key Insight: PVR Forum Mall generates Rs.2,30,720 in revenue,
A7: Cinepolis City Centre | B7: 196540 | D7: indicating strong revenue contribution from this theater.
A8: Cinepolis Forum Mall | B8: 217780
A9: Cinepolis Grand Mall | B9: 201920
A10: City Pride City Centre | B10: 201840
A11: City Pride Forum Mall | B11: 184560
A12: City Pride Grand Mall | B12: 182340
A13: INOX City Centre | B13: 224240
A14: INOX Forum Mall | B14: 223940
A15: INOX Grand Mall | B15: 230680
A16: Miraj Cinemas City Centre | B16: 179000
A17: Miraj Cinemas Forum Mall | B17: 211780
A18: Miraj Cinemas Grand Mall | B18: 165380
A19: MovieMax City Centre | B19: 170760
... A28: Grand Total | B28: 4850160

Sheet Agewise_Analysis
A2: Agewise Booking Analysis
A3: Age Group | B3: Count of Booking_ID | C3: Sum of Total Amount
A4: Above 45 | B4: 2209 | C4: 1818440
A5: Middle Age | B5: 2104 | C5: 1675940
A6: Youngster | B6: 1687 | C6: 1355780
A7: Grand Total | B7: 6000 | C7: 4850160
A10: Key Insight: The analysis shows that customers above 45 have the
A11: highest number of bookings, followed by the middle-age group,
A12: while younger customers have fewer bookings.

Sheet City_Analysis
A2: Booking by Cinema City
A3: Cinema City | B3: Count of Booking_ID
A4: Ahmedabad | B4: 395
A5: Bengaluru | B5: 363
A6: Chennai | B6: 368 | D6: Key Insight: Pune has the highest number of bookings with 428,followed
A7: Coimbatore | B7: 358 | D7: kolkata with 404 and kochi with 397, indicating strong movie-booking
A8: Delhi | B8: 383 | D8: demand in these cities.
A9: Hyderabad | B9: 353
A10: Kochi | B10: 397
A11: Kolkata | B11: 404
A12: Madurai | B12: 361
A13: Mumbai | B13: 370
A14: Mysuru | B14: 370
A15: Noida | B15: 350
A16: Pune | B16: 428
A17: Salem | B17: 337
A18: Thiruvananthapuram | B18: 383
A19: Vijayawada | B19: 380
A20: Grand Total | B20: 6000

Sheet Payment_Analysis
A2: Payment Analysis
A3: Payment Method | B3: Count of Booking_ID
A4: Credit Card | B4: 1219
A5: Debit Card | B5: 1177
A6: Net Banking | B6: 1181
A7: UPI | B7: 1216
A8: Wallet | B8: 1207
A9: Grand Total | B9: 6000
A11: Key Insight: Credit card is the most used payement method
A12: with 1,219 bookings, followed closely by UPI and Wallet.

Sheet Movie_Analysis
A2: Movie wise Revenue
A3: Movie Name | B3: Sum of Total Amount | C3: Count of Booking_ID
A4: 12th Fail | B4: 99720 | C4: 124
A5: 777 Charlie | B5: 106800 | C5: 131 | F5: Key Insight: The movie analysis compares booking volume and
A6: Aavesham | B6: 86700 | C6: 122 | F6: total revenue to identify movies with higher audience demand
A7: Amaran | B7: 174680 | C7: 217 | F7: and stronger revenue contribution.
A8: Animal | B8: 100320 | C8: 125
A9: Arjun Reddy | B9: 99820 | C9: 111
A10: Avengers Endgame | B10: 86320 | C10: 119
A11: Baahubali 2 | B11: 105860 | C11: 120
A12: Bangalore Days | B12: 110520 | C12: 137
A13: Barbie | B13: 105660 | C13: 124
A14: Bhool Bhulaiyaa 2 | B14: 93880 | C14: 118
A15: Captain Miller | B15: 185560 | C15: 237
A16: Drishyam 2 | B16: 93900 | C16: 120
A17: Dune: Part Two | B17: 103880 | C17: 113
A18: Good Night | B18: 171980 | C18: 226
A19: Hi Nanna | B19: 92440 | C19: 115
... A44: Grand Total | B44: 4850160 | C44: 6000

Sheet Daytype_Analysis
A2: Day Type Analysis
A3: Day_Type | B3: Count of Booking_ID
A4: Weekday | B4: 4296
A5: Weekend | B5: 1704
A6: Grand Total | B6: 6000
A8: Key Insight: | B8: This analysis shows that weekday bookings are
A9: significantly higher than weekend bookings.This indicates
A10: that,in this dataset, booking activity is higher on weekdays.

Sheet Entertainment_Booking_Analysis
A1: Booking_ID | B1: Booking_Date | C1: Show_Date | D1: Show_time | E1: Day_type | F1: Month | G1: Movie_id | H1: Movie_Name | I1: Genre | J1: Language | K1: Rating | L1: Cinema_id | M1: Cinema_name | N1: City | O1: Ticket Booked | P1: Ticket_price | Q1: Total Amount | R1: Payment_method | S1: Customer_Age | T1: Gender | U1: Age_group | V1: Booking_category
A2: B000001 | B2: 46139 | C2: 46139 | D2: 0.9375 | E2: =IF(WEEKDAY(B2,2)<=5,"Weekday","Weekend") -> Weekday | F2: =TEXT(B2,"mmm") -> Apr | G2: =_xlfn.XLOOKUP(A2,Booking_data!$A$1:$A$6001,Booking_data!$D$1:$D$6001,"not found") -> M038 | H2: =_xlfn.XLOOKUP(G2,Movies_data!$A$1:$A$41,Movies_data!$B$1:$B$41,"not found") -> Barbie | I2: =_xlfn.XLOOKUP(G2,Movies_data!$A$1:$A$41,Movies_data!$D$1:$D$41,"not found") -> Comedy | J2: =_xlfn.XLOOKUP(G2,Movies_data!$A$1:$A$41,Movies_data!$C$1:$C$41,"not found") -> English | K2: =_xlfn.XLOOKUP(G2,Movies_data!$A$1:$A$41,Movies_data!$H$1:$H$41,"Not Found") -> 6.8 | L2: =_xlfn.XLOOKUP(A2,Booking_data!$A$1:$A$6001,Booking_data!$E$1:$E$6001,"not Found") -> C162 | M2: =_xlfn.XLOOKUP(L2,Cinemas_data!$A$1:$A$49,Cinemas_data!$I$1:$I$49,"not Found") -> Cinepolis Grand Mall | N2: =_xlfn.XLOOKUP(L2,Cinemas_data!$A$1:$A$49,Cinemas_data!$C$1:$C$49,"not Found") -> Thiruvananthapuram | O2: =_xlfn.XLOOKUP(A2,Booking_data!$A$1:$A$6001,Booking_data!$H$1:$H$6001,"not found") -> 6 | P2: =_xlfn.XLOOKUP(A2,Booking_data!$A$1:$A$6001,Booking_data!$I$1:$I$6001,"not Found") -> 160 | Q2: =O2*P2 -> 960 | R2: =_xlfn.XLOOKUP(A2,Booking_data!$A$1:$A$6001,Booking_data!$L$1:$L$6001,"Not Found") -> Wallet | S2: =_xlfn.XLOOKUP(A2,Booking_data!$A$1:$A$6001,Booking_data!$N$1:$N$6001,"not Found") -> 24 | T2: =_xlfn.XLOOKUP(A2,Booking_data!$A$1:$A$6001,Booking_data!$O$1:$O$6001,"Not Found") -> Other | U2: =IF(S2<18,"Below 18",IF(S2<30,"Youngster",IF(S2<45,"Middle Age","Above 45"))) -> Youngster | V2: =IF(O2<=2,"Low Booking",IF(O2<=4,"Medium Booking","High Booking")) -> High Booking
A3: B000002 | B3: 46062 | C3: 46067 | D3: 0.64583333 | E3: =IF(WEEKDAY(B3,2)<=5,"Weekday","Weekend") -> Weekday | F3: =TEXT(B3,"mmm") -> Feb | G3: =_xlfn.XLOOKUP(A3,Booking_data!$A$1:$A$6001,Booking_data!$D$1:$D$6001,"not found") -> M029 | H3: =_xlfn.XLOOKUP(G3,Movies_data!$A$1:$A$41,Movies_data!$B$1:$B$41,"not found") -> 777 Charlie | I3: =_xlfn.XLOOKUP(G3,Movies_data!$A$1:$A$41,Movies_data!$D$1:$D$41,"not found") -> Adventure | J3: =_xlfn.XLOOKUP(G3,Movies_data!$A$1:$A$41,Movies_data!$C$1:$C$41,"not found") -> Kannada | K3: =_xlfn.XLOOKUP(G3,Movies_data!$A$1:$A$41,Movies_data!$H$1:$H$41,"Not Found") -> 8.7 | L3: =_xlfn.XLOOKUP(A3,Booking_data!$A$1:$A$6001,Booking_data!$E$1:$E$6001,"not Found") -> C122 | M3: =_xlfn.XLOOKUP(L3,Cinemas_data!$A$1:$A$49,Cinemas_data!$I$1:$I$49,"not Found") -> Asian Cinemas Grand Mall | N3: =_xlfn.XLOOKUP(L3,Cinemas_data!$A$1:$A$49,Cinemas_data!$C$1:$C$49,"not Found") -> Noida | O3: =_xlfn.XLOOKUP(A3,Booking_data!$A$1:$A$6001,Booking_data!$H$1:$H$6001,"not found") -> 5 | P3: =_xlfn.XLOOKUP(A3,Booking_data!$A$1:$A$6001,Booking_data!$I$1:$I$6001,"not Found") -> 360 | Q3: =O3*P3 -> 1800 | R3: =_xlfn.XLOOKUP(A3,Booking_data!$A$1:$A$6001,Booking_data!$L$1:$L$6001,"Not Found") -> Debit Card | S3: =_xlfn.XLOOKUP(A3,Booking_data!$A$1:$A$6001,Booking_data!$N$1:$N$6001,"not Found") -> 25 | T3: =_xlfn.XLOOKUP(A3,Booking_data!$A$1:$A$6001,Booking_data!$O$1:$O$6001,"Not Found") -> Male | U3: =IF(S3<18,"Below 18",IF(S3<30,"Youngster",IF(S3<45,"Middle Age","Above 45"))) -> Youngster | V3: =IF(O3<=2,"Low Booking",IF(O3<=4,"Medium Booking","High Booking")) -> High Booking
A4: B000003 | B4: 46084 | C4: 46085 | D4: 0.77083333 | E4: =IF(WEEKDAY(B4,2)<=5,"Weekday","Weekend") -> Weekday | F4: =TEXT(B4,"mmm") -> Mar | G4: =_xlfn.XLOOKUP(A4,Booking_data!$A$1:$A$6001,Booking_data!$D$1:$D$6001,"not found") -> M003 | H4: =_xlfn.XLOOKUP(G4,Movies_data!$A$1:$A$41,Movies_data!$B$1:$B$41,"not found") -> Vikram | I4: =_xlfn.XLOOKUP(G4,Movies_data!$A$1:$A$41,Movies_data!$D$1:$D$41,"not found") -> Action | J4: =_xlfn.XLOOKUP(G4,Movies_data!$A$1:$A$41,Movies_data!$C$1:$C$41,"not found") -> Tamil | K4: =_xlfn.XLOOKUP(G4,Movies_data!$A$1:$A$41,Movies_data!$H$1:$H$41,"Not Found") -> 8.3 | L4: =_xlfn.XLOOKUP(A4,Booking_data!$A$1:$A$6001,Booking_data!$E$1:$E$6001,"not Found") -> C112 | M4: =_xlfn.XLOOKUP(L4,Cinemas_data!$A$1:$A$49,Cinemas_data!$I$1:$I$49,"not Found") -> MovieMax Grand Mall | N4: =_xlfn.XLOOKUP(L4,Cinemas_data!$A$1:$A$49,Cinemas_data!$C$1:$C$49,"not Found") -> Delhi | O4: =_xlfn.XLOOKUP(A4,Booking_data!$A$1:$A$6001,Booking_data!$H$1:$H$6001,"not found") -> 6 | P4: =_xlfn.XLOOKUP(A4,Booking_data!$A$1:$A$6001,Booking_data!$I$1:$I$6001,"not Found") -> 240 | Q4: =O4*P4 -> 1440 | R4: =_xlfn.XLOOKUP(A4,Booking_data!$A$1:$A$6001,Booking_data!$L$1:$L$6001,"Not Found") -> Credit Card | S4: =_xlfn.XLOOKUP(A4,Booking_data!$A$1:$A$6001,Booking_data!$N$1:$N$6001,"not Found") -> 60 | T4: =_xlfn.XLOOKUP(A4,Booking_data!$A$1:$A$6001,Booking_data!$O$1:$O$6001,"Not Found") -> Female | U4: =IF(S4<18,"Below 18",IF(S4<30,"Youngster",IF(S4<45,"Middle Age","Above 45"))) -> Above 45 | V4: =IF(O4<=2,"Low Booking",IF(O4<=4,"Medium Booking","High Booking")) -> High Booking
A5: B000004 | B5: 46084 | C5: 46080 | D5: 0.39583333 | E5: =IF(WEEKDAY(B5,2)<=5,"Weekday","Weekend") -> Weekday | F5: =TEXT(B5,"mmm") -> Mar | G5: =_xlfn.XLOOKUP(A5,Booking_data!$A$1:$A$6001,Booking_data!$D$1:$D$6001,"not found") -> M026 | H5: =_xlfn.XLOOKUP(G5,Movies_data!$A$1:$A$41,Movies_data!$B$1:$B$41,"not found") -> Drishyam 2 | I5: =_xlfn.XLOOKUP(G5,Movies_data!$A$1:$A$41,Movies_data!$D$1:$D$41,"not found") -> Thriller | J5: =_xlfn.XLOOKUP(G5,Movies_data!$A$1:$A$41,Movies_data!$C$1:$C$41,"not found") -> Hindi | K5: =_xlfn.XLOOKUP(G5,Movies_data!$A$1:$A$41,Movies_data!$H$1:$H$41,"Not Found") -> 8.2 | L5: =_xlfn.XLOOKUP(A5,Booking_data!$A$1:$A$6001,Booking_data!$E$1:$E$6001,"not Found") -> C092 | M5: =_xlfn.XLOOKUP(L5,Cinemas_data!$A$1:$A$49,Cinemas_data!$I$1:$I$49,"not Found") -> Miraj Cinemas Grand Mall | N5: =_xlfn.XLOOKUP(L5,Cinemas_data!$A$1:$A$49,Cinemas_data!$C$1:$C$49,"not Found") -> Mumbai | O5: =_xlfn.XLOOKUP(A5,Booking_data!$A$1:$A$6001,Booking_data!$H$1:$H$6001,"not found") -> 3 | P5: =_xlfn.XLOOKUP(A5,Booking_data!$A$1:$A$6001,Booking_data!$I$1:$I$6001,"not Found") -> 160 | Q5: =O5*P5 -> 480 | R5: =_xlfn.XLOOKUP(A5,Booking_data!$A$1:$A$6001,Booking_data!$L$1:$L$6001,"Not Found") -> UPI | S5: =_xlfn.XLOOKUP(A5,Booking_data!$A$1:$A$6001,Booking_data!$N$1:$N$6001,"not Found") -> 32 | T5: =_xlfn.XLOOKUP(A5,Booking_data!$A$1:$A$6001,Booking_data!$O$1:$O$6001,"Not Found") -> Other | U5: =IF(S5<18,"Below 18",IF(S5<30,"Youngster",IF(S5<45,"Middle Age","Above 45"))) -> Middle Age | V5: =IF(O5<=2,"Low Booking",IF(O5<=4,"Medium Booking","High Booking")) -> Medium Booking
A6: B000005 | B6: 46084 | C6: 46176 | D6: 0.88541667 | E6: =IF(WEEKDAY(B6,2)<=5,"Weekday","Weekend") -> Weekday | F6: =TEXT(B6,"mmm") -> Mar | G6: =_xlfn.XLOOKUP(A6,Booking_data!$A$1:$A$6001,Booking_data!$D$1:$D$6001,"not found") -> M001 | H6: =_xlfn.XLOOKUP(G6,Movies_data!$A$1:$A$41,Movies_data!$B$1:$B$41,"not found") -> Leo | I6: =_xlfn.XLOOKUP(G6,Movies_data!$A$1:$A$41,Movies_data!$D$1:$D$41,"not found") -> Action | J6: =_xlfn.XLOOKUP(G6,Movies_data!$A$1:$A$41,Movies_data!$C$1:$C$41,"not found") -> Tamil | K6: =_xlfn.XLOOKUP(G6,Movies_data!$A$1:$A$41,Movies_data!$H$1:$H$41,"Not Found") -> 8 | L6: =_xlfn.XLOOKUP(A6,Booking_data!$A$1:$A$6001,Booking_data!$E$1:$E$6001,"not Found") -> C161 | M6: =_xlfn.XLOOKUP(L6,Cinemas_data!$A$1:$A$49,Cinemas_data!$I$1:$I$49,"not Found") -> INOX City Centre | N6: =_xlfn.XLOOKUP(L6,Cinemas_data!$A$1:$A$49,Cinemas_data!$C$1:$C$49,"not Found") -> Thiruvananthapuram | O6: =_xlfn.XLOOKUP(A6,Booking_data!$A$1:$A$6001,Booking_data!$H$1:$H$6001,"not found") -> 2 | P6: =_xlfn.XLOOKUP(A6,Booking_data!$A$1:$A$6001,Booking_data!$I$1:$I$6001,"not Found") -> 280 | Q6: =O6*P6 -> 560 | R6: =_xlfn.XLOOKUP(A6,Booking_data!$A$1:$A$6001,Booking_data!$L$1:$L$6001,"Not Found") -> Debit Card | S6: =_xlfn.XLOOKUP(A6,Booking_data!$A$1:$A$6001,Booking_data!$N$1:$N$6001,"not Found") -> 22 | T6: =_xlfn.XLOOKUP(A6,Booking_data!$A$1:$A$6001,Booking_data!$O$1:$O$6001,"Not Found") -> Other | U6: =IF(S6<18,"Below 18",IF(S6<30,"Youngster",IF(S6<45,"Middle Age","Above 45"))) -> Youngster | V6: =IF(O6<=2,"Low Booking",IF(O6<=4,"Medium Booking","High Booking")) -> Low Booking
A7: B000006 | B7: 46084 | C7: 46079 | D7: 0.39583333 | E7: =IF(WEEKDAY(B7,2)<=5,"Weekday","Weekend") -> Weekday | F7: =TEXT(B7,"mmm") -> Mar | G7: =_xlfn.XLOOKUP(A7,Booking_data!$A$1:$A$6001,Booking_data!$D$1:$D$6001,"not found") -> M027 | H7: =_xlfn.XLOOKUP(G7,Movies_data!$A$1:$A$41,Movies_data!$B$1:$B$41,"not found") -> KGF Chapter 2 | I7: =_xlfn.XLOOKUP(G7,Movies_data!$A$1:$A$41,Movies_data!$D$1:$D$41,"not found") -> Action | J7: =_xlfn.XLOOKUP(G7,Movies_data!$A$1:$A$41,Movies_data!$C$1:$C$41,"not found") -> Kannada | K7: =_xlfn.XLOOKUP(G7,Movies_data!$A$1:$A$41,Movies_data!$H$1:$H$41,"Not Found") -> 8.3 | L7: =_xlfn.XLOOKUP(A7,Booking_data!$A$1:$A$6001,Booking_data!$E$1:$E$6001,"not Found") -> C131 | M7: =_xlfn.XLOOKUP(L7,Cinemas_data!$A$1:$A$49,Cinemas_data!$I$1:$I$49,"not Found") -> Asian Cinemas City Centre | N7: =_xlfn.XLOOKUP(L7,Cinemas_data!$A$1:$A$49,Cinemas_data!$C$1:$C$49,"not Found") -> Kolkata | O7: =_xlfn.XLOOKUP(A7,Booking_data!$A$1:$A$6001,Booking_data!$H$1:$H$6001,"not found") -> 3 | P7: =_xlfn.XLOOKUP(A7,Booking_data!$A$1:$A$6001,Booking_data!$I$1:$I$6001,"not Found") -> 340 | Q7: =O7*P7 -> 1020 | R7: =_xlfn.XLOOKUP(A7,Booking_data!$A$1:$A$6001,Booking_data!$L$1:$L$6001,"Not Found") -> Net Banking | S7: =_xlfn.XLOOKUP(A7,Booking_data!$A$1:$A$6001,Booking_data!$N$1:$N$6001,"not Found") -> 30 | T7: =_xlfn.XLOOKUP(A7,Booking_data!$A$1:$A$6001,Booking_data!$O$1:$O$6001,"Not Found") -> Female | U7: =IF(S7<18,"Below 18",IF(S7<30,"Youngster",IF(S7<45,"Middle Age","Above 45"))) -> Middle Age | V7: =IF(O7<=2,"Low Booking",IF(O7<=4,"Medium Booking","High Booking")) -> Medium Booking
A8: B000007 | B8: 46084 | C8: 46135 | D8: 0.53125 | E8: =IF(WEEKDAY(B8,2)<=5,"Weekday","Weekend") -> Weekday | F8: =TEXT(B8,"mmm") -> Mar | G8: =_xlfn.XLOOKUP(A8,Booking_data!$A$1:$A$6001,Booking_data!$D$1:$D$6001,"not found") -> M034 | H8: =_xlfn.XLOOKUP(G8,Movies_data!$A$1:$A$41,Movies_data!$B$1:$B$41,"not found") -> Manjummel Boys | I8: =_xlfn.XLOOKUP(G8,Movies_data!$A$1:$A$41,Movies_data!$D$1:$D$41,"not found") -> Adventure | J8: =_xlfn.XLOOKUP(G8,Movies_data!$A$1:$A$41,Movies_data!$C$1:$C$41,"not found") -> Malayalam | K8: =_xlfn.XLOOKUP(G8,Movies_data!$A$1:$A$41,Movies_data!$H$1:$H$41,"Not Found") -> 8.3 | L8: =_xlfn.XLOOKUP(A8,Booking_data!$A$1:$A$6001,Booking_data!$E$1:$E$6001,"not Found") -> C021 | M8: =_xlfn.XLOOKUP(L8,Cinemas_data!$A$1:$A$49,Cinemas_data!$I$1:$I$49,"not Found") -> Miraj Cinemas City Centre | N8: =_xlfn.XLOOKUP(L8,Cinemas_data!$A$1:$A$49,Cinemas_data!$C$1:$C$49,"not Found") -> Coimbatore | O8: =_xlfn.XLOOKUP(A8,Booking_data!$A$1:$A$6001,Booking_data!$H$1:$H$6001,"not found") -> 1 | P8: =_xlfn.XLOOKUP(A8,Booking_data!$A$1:$A$6001,Booking_data!$I$1:$I$6001,"not Found") -> 220 | Q8: =O8*P8 -> 220 | R8: =_xlfn.XLOOKUP(A8,Booking_data!$A$1:$A$6001,Booking_data!$L$1:$L$6001,"Not Found") -> Credit Card | S8: =_xlfn.XLOOKUP(A8,Booking_data!$A$1:$A$6001,Booking_data!$N$1:$N$6001,"not Found") -> 24 | T8: =_xlfn.XLOOKUP(A8,Booking_data!$A$1:$A$6001,Booking_data!$O$1:$O$6001,"Not Found") -> Other | U8: =IF(S8<18,"Below 18",IF(S8<30,"Youngster",IF(S8<45,"Middle Age","Above 45"))) -> Youngster | V8: =IF(O8<=2,"Low Booking",IF(O8<=4,"Medium Booking","High Booking")) -> Low Booking
A9: B000008 | B9: 46084 | C9: 46064 | D9: 0.39583333 | E9: =IF(WEEKDAY(B9,2)<=5,"Weekday","Weekend") -> Weekday | F9: =TEXT(B9,"mmm") -> Mar | G9: =_xlfn.XLOOKUP(A9,Booking_data!$A$1:$A$6001,Booking_data!$D$1:$D$6001,"not found") -> M005 | H9: =_xlfn.XLOOKUP(G9,Movies_data!$A$1:$A$41,Movies_data!$B$1:$B$41,"not found") -> Ponniyin Selvan II | I9: =_xlfn.XLOOKUP(G9,Movies_data!$A$1:$A$41,Movies_data!$D$1:$D$41,"not found") -> Drama | J9: =_xlfn.XLOOKUP(G9,Movies_data!$A$1:$A$41,Movies_data!$C$1:$C$41,"not found") -> Tamil | K9: =_xlfn.XLOOKUP(G9,Movies_data!$A$1:$A$41,Movies_data!$H$1:$H$41,"Not Found") -> 7.3 | L9: =_xlfn.XLOOKUP(A9,Booking_data!$A$1:$A$6001,Booking_data!$E$1:$E$6001,"not Found") -> C103 | M9: =_xlfn.XLOOKUP(L9,Cinemas_data!$A$1:$A$49,Cinemas_data!$I$1:$I$49,"not Found") -> MovieMax Forum Mall | N9: =_xlfn.XLOOKUP(L9,Cinemas_data!$A$1:$A$49,Cinemas_data!$C$1:$C$49,"not Found") -> Pune | O9: =_xlfn.XLOOKUP(A9,Booking_data!$A$1:$A$6001,Booking_data!$H$1:$H$6001,"not found") -> 5 | P9: =_xlfn.XLOOKUP(A9,Booking_data!$A$1:$A$6001,Booking_data!$I$1:$I$6001,"not Found") -> 180 | Q9: =O9*P9 -> 900 | R9: =_xlfn.XLOOKUP(A9,Booking_data!$A$1:$A$6001,Booking_data!$L$1:$L$6001,"Not Found") -> Wallet | S9: =_xlfn.XLOOKUP(A9,Booking_data!$A$1:$A$6001,Booking_data!$N$1:$N$6001,"not Found") -> 53 | T9: =_xlfn.XLOOKUP(A9,Booking_data!$A$1:$A$6001,Booking_data!$O$1:$O$6001,"Not Found") -> Male | U9: =IF(S9<18,"Below 18",IF(S9<30,"Youngster",IF(S9<45,"Middle Age","Above 45"))) -> Above 45 | V9: =IF(O9<=2,"Low Booking",IF(O9<=4,"Medium Booking","High Booking")) -> High Booking
A10: B000009 | B10: 46084 | C10: 46085 | D10: 0.77083333 | E10: =IF(WEEKDAY(B10,2)<=5,"Weekday","Weekend") -> Weekday | F10: =TEXT(B10,"mmm") -> Mar | G10: =_xlfn.XLOOKUP(A10,Booking_data!$A$1:$A$6001,Booking_data!$D$1:$D$6001,"not found") -> M011 | H10: =_xlfn.XLOOKUP(G10,Movies_data!$A$1:$A$41,Movies_data!$B$1:$B$41,"not found") -> Pushpa 2 | I10: =_xlfn.XLOOKUP(G10,Movies_data!$A$1:$A$41,Movies_data!$D$1:$D$41,"not found") -> Action | J10: =_xlfn.XLOOKUP(G10,Movies_data!$A$1:$A$41,Movies_data!$C$1:$C$41,"not found") -> Telugu | K10: =_xlfn.XLOOKUP(G10,Movies_data!$A$1:$A$41,Movies_data!$H$1:$H$41,"Not Found") -> 6.1 | L10: =_xlfn.XLOOKUP(A10,Booking_data!$A$1:$A$6001,Booking_data!$E$1:$E$6001,"not Found") -> C111 | M10: =_xlfn.XLOOKUP(L10,Cinemas_data!$A$1:$A$49,Cinemas_data!$I$1:$I$49,"not Found") -> Mukta A2 Cinemas City Centre | N10: =_xlfn.XLOOKUP(L10,Cinemas_data!$A$1:$A$49,Cinemas_data!$C$1:$C$49,"not Found") -> Delhi | O10: =_xlfn.XLOOKUP(A10,Booking_data!$A$1:$A$6001,Booking_data!$H$1:$H$6001,"not found") -> 5 | P10: =_xlfn.XLOOKUP(A10,Booking_data!$A$1:$A$6001,Booking_data!$I$1:$I$6001,"not Found") -> 180 | Q10: =O10*P10 -> 900 | R10: =_xlfn.XLOOKUP(A10,Booking_data!$A$1:$A$6001,Booking_data!$L$1:$L$6001,"Not Found") -> Net Banking | S10: =_xlfn.XLOOKUP(A10,Booking_data!$A$1:$A$6001,Booking_data!$N$1:$N$6001,"not Found") -> 18 | T10: =_xlfn.XLOOKUP(A10,Booking_data!$A$1:$A$6001,Booking_data!$O$1:$O$6001,"Not Found") -> Female | U10: =IF(S10<18,"Below 18",IF(S10<30,"Youngster",IF(S10<45,"Middle Age","Above 45"))) -> Youngster | V10: =IF(O10<=2,"Low Booking",IF(O10<=4,"Medium Booking","High Booking")) -> High Booking
A11: B000010 | B11: 46084 | C11: 46208 | D11: 0.39583333 | E11: =IF(WEEKDAY(B11,2)<=5,"Weekday","Weekend") -> Weekday | F11: =TEXT(B11,"mmm") -> Mar | G11: =_xlfn.XLOOKUP(A11,Booking_data!$A$1:$A$6001,Booking_data!$D$1:$D$6001,"not found") -> M004 | H11: =_xlfn.XLOOKUP(G11,Movies_data!$A$1:$A$41,Movies_data!$B$1:$B$41,"not found") -> Ponniyin Selvan I | I11: =_xlfn.XLOOKUP(G11,Movies_data!$A$1:$A$41,Movies_data!$D$1:$D$41,"not found") -> Drama | J11: =_xlfn.XLOOKUP(G11,Movies_data!$A$1:$A$41,Movies_data!$C$1:$C$41,"not found") -> Tamil | K11: =_xlfn.XLOOKUP(G11,Movies_data!$A$1:$A$41,Movies_data!$H$1:$H$41,"Not Found") -> 7.6 | L11: =_xlfn.XLOOKUP(A11,Booking_data!$A$1:$A$6001,Booking_data!$E$1:$E$6001,"not Found") -> C071 | M11: =_xlfn.XLOOKUP(L11,Cinemas_data!$A$1:$A$49,Cinemas_data!$I$1:$I$49,"not Found") -> PVR City Centre | N11: =_xlfn.XLOOKUP(L11,Cinemas_data!$A$1:$A$49,Cinemas_data!$C$1:$C$49,"not Found") -> Hyderabad | O11: =_xlfn.XLOOKUP(A11,Booking_data!$A$1:$A$6001,Booking_data!$H$1:$H$6001,"not found") -> 6 | P11: =_xlfn.XLOOKUP(A11,Booking_data!$A$1:$A$6001,Booking_data!$I$1:$I$6001,"not Found") -> 180 | Q11: =O11*P11 -> 1080 | R11: =_xlfn.XLOOKUP(A11,Booking_data!$A$1:$A$6001,Booking_data!$L$1:$L$6001,"Not Found") -> Wallet | S11: =_xlfn.XLOOKUP(A11,Booking_data!$A$1:$A$6001,Booking_data!$N$1:$N$6001,"not Found") -> 38 | T11: =_xlfn.XLOOKUP(A11,Booking_data!$A$1:$A$6001,Booking_data!$O$1:$O$6001,"Not Found") -> Female | U11: =IF(S11<18,"Below 18",IF(S11<30,"Youngster",IF(S11<45,"Middle Age","Above 45"))) -> Middle Age | V11: =IF(O11<=2,"Low Booking",IF(O11<=4,"Medium Booking","High Booking")) -> High Booking
A12: B000011 | B12: 46084 | C12: 46038 | D12: 0.53125 | E12: =IF(WEEKDAY(B12,2)<=5,"Weekday","Weekend") -> Weekday | F12: =TEXT(B12,"mmm") -> Mar | G12: =_xlfn.XLOOKUP(A12,Booking_data!$A$1:$A$6001,Booking_data!$D$1:$D$6001,"not found") -> M033 | H12: =_xlfn.XLOOKUP(G12,Movies_data!$A$1:$A$41,Movies_data!$B$1:$B$41,"not found") -> Lucifer | I12: =_xlfn.XLOOKUP(G12,Movies_data!$A$1:$A$41,Movies_data!$D$1:$D$41,"not found") -> Action | J12: =_xlfn.XLOOKUP(G12,Movies_data!$A$1:$A$41,Movies_data!$C$1:$C$41,"not found") -> Malayalam | K12: =_xlfn.XLOOKUP(G12,Movies_data!$A$1:$A$41,Movies_data!$H$1:$H$41,"Not Found") -> 7.5 | L12: =_xlfn.XLOOKUP(A12,Booking_data!$A$1:$A$6001,Booking_data!$E$1:$E$6001,"not Found") -> C022 | M12: =_xlfn.XLOOKUP(L12,Cinemas_data!$A$1:$A$49,Cinemas_data!$I$1:$I$49,"not Found") -> Mukta A2 Cinemas Grand Mall | N12: =_xlfn.XLOOKUP(L12,Cinemas_data!$A$1:$A$49,Cinemas_data!$C$1:$C$49,"not Found") -> Coimbatore | O12: =_xlfn.XLOOKUP(A12,Booking_data!$A$1:$A$6001,Booking_data!$H$1:$H$6001,"not found") -> 1 | P12: =_xlfn.XLOOKUP(A12,Booking_data!$A$1:$A$6001,Booking_data!$I$1:$I$6001,"not Found") -> 380 | Q12: =O12*P12 -> 380 | R12: =_xlfn.XLOOKUP(A12,Booking_data!$A$1:$A$6001,Booking_data!$L$1:$L$6001,"Not Found") -> Wallet | S12: =_xlfn.XLOOKUP(A12,Booking_data!$A$1:$A$6001,Booking_data!$N$1:$N$6001,"not Found") -> 54 | T12: =_xlfn.XLOOKUP(A12,Booking_data!$A$1:$A$6001,Booking_data!$O$1:$O$6001,"Not Found") -> Male | U12: =IF(S12<18,"Below 18",IF(S12<30,"Youngster",IF(S12<45,"Middle Age","Above 45"))) -> Above 45 | V12: =IF(O12<=2,"Low Booking",IF(O12<=4,"Medium Booking","High Booking")) -> Low Booking
A13: B000012 | B13: 46084 | C13: 46196 | D13: 0.77083333 | E13: =IF(WEEKDAY(B13,2)<=5,"Weekday","Weekend") -> Weekday | F13: =TEXT(B13,"mmm") -> Mar | G13: =_xlfn.XLOOKUP(A13,Booking_data!$A$1:$A$6001,Booking_data!$D$1:$D$6001,"not found") -> M037 | H13: =_xlfn.XLOOKUP(G13,Movies_data!$A$1:$A$41,Movies_data!$B$1:$B$41,"not found") -> Oppenheimer | I13: =_xlfn.XLOOKUP(G13,Movies_data!$A$1:$A$41,Movies_data!$D$1:$D$41,"not found") -> Biography | J13: =_xlfn.XLOOKUP(G13,Movies_data!$A$1:$A$41,Movies_data!$C$1:$C$41,"not found") -> English | K13: =_xlfn.XLOOKUP(G13,Movies_data!$A$1:$A$41,Movies_data!$H$1:$H$41,"Not Found") -> 8.5 | L13: =_xlfn.XLOOKUP(A13,Booking_data!$A$1:$A$6001,Booking_data!$E$1:$E$6001,"not Found") -> C052 | M13: =_xlfn.XLOOKUP(L13,Cinemas_data!$A$1:$A$49,Cinemas_data!$I$1:$I$49,"not Found") -> City Pride Grand Mall | N13: =_xlfn.XLOOKUP(L13,Cinemas_data!$A$1:$A$49,Cinemas_data!$C$1:$C$49,"not Found") -> Bengaluru | O13: =_xlfn.XLOOKUP(A13,Booking_data!$A$1:$A$6001,Booking_data!$H$1:$H$6001,"not found") -> 2 | P13: =_xlfn.XLOOKUP(A13,Booking_data!$A$1:$A$6001,Booking_data!$I$1:$I$6001,"not Found") -> 200 | Q13: =O13*P13 -> 400 | R13: =_xlfn.XLOOKUP(A13,Booking_data!$A$1:$A$6001,Booking_data!$L$1:$L$6001,"Not Found") -> UPI | S13: =_xlfn.XLOOKUP(A13,Booking_data!$A$1:$A$6001,Booking_data!$N$1:$N$6001,"not Found") -> 37 | T13: =_xlfn.XLOOKUP(A13,Booking_data!$A$1:$A$6001,Booking_data!$O$1:$O$6001,"Not Found") -> Male | U13: =IF(S13<18,"Below 18",IF(S13<30,"Youngster",IF(S13<45,"Middle Age","Above 45"))) -> Middle Age | V13: =IF(O13<=2,"Low Booking",IF(O13<=4,"Medium Booking","High Booking")) -> Low Booking
... A6001: B006000 | B6001: 46084 | C6001: 46081 | D6001: 0.77083333 | E6001: =IF(WEEKDAY(B6001,2)<=5,"Weekday","Weekend") -> Weekday | F6001: =TEXT(B6001,"mmm") -> Mar | G6001: =_xlfn.XLOOKUP(A6001,Booking_data!$A$1:$A$6001,Booking_data!$D$1:$D$6001,"not found") -> M007 | H6001: =_xlfn.XLOOKUP(G6001,Movies_data!$A$1:$A$41,Movies_data!$B$1:$B$41,"not found") -> Good Night | I6001: =_xlfn.XLOOKUP(G6001,Movies_data!$A$1:$A$41,Movies_data!$D$1:$D$41,"not found") -> Comedy | J6001: =_xlfn.XLOOKUP(G6001,Movies_data!$A$1:$A$41,Movies_data!$C$1:$C$41,"not found") -> Tamil | K6001: =_xlfn.XLOOKUP(G6001,Movies_data!$A$1:$A$41,Movies_data!$H$1:$H$41,"Not Found") -> 8 | L6001: =_xlfn.XLOOKUP(A6001,Booking_data!$A$1:$A$6001,Booking_data!$E$1:$E$6001,"not Found") -> C072 | M6001: =_xlfn.XLOOKUP(L6001,Cinemas_data!$A$1:$A$49,Cinemas_data!$I$1:$I$49,"not Found") -> INOX Grand Mall | N6001: =_xlfn.XLOOKUP(L6001,Cinemas_data!$A$1:$A$49,Cinemas_data!$C$1:$C$49,"not Found") -> Hyderabad | O6001: =_xlfn.XLOOKUP(A6001,Booking_data!$A$1:$A$6001,Booking_data!$H$1:$H$6001,"not found") -> 3 | P6001: =_xlfn.XLOOKUP(A6001,Booking_data!$A$1:$A$6001,Booking_data!$I$1:$I$6001,"not Found") -> 380 | Q6001: =O6001*P6001 -> 1140 | R6001: =_xlfn.XLOOKUP(A6001,Booking_data!$A$1:$A$6001,Booking_data!$L$1:$L$6001,"Not Found") -> UPI | S6001: =_xlfn.XLOOKUP(A6001,Booking_data!$A$1:$A$6001,Booking_data!$N$1:$N$6001,"not Found") -> 33 | T6001: =_xlfn.XLOOKUP(A6001,Booking_data!$A$1:$A$6001,Booking_data!$O$1:$O$6001,"Not Found") -> Other | U6001: =IF(S6001<18,"Below 18",IF(S6001<30,"Youngster",IF(S6001<45,"Middle Age","Above 45"))) -> Middle Age | V6001: =IF(O6001<=2,"Low Booking",IF(O6001<=4,"Medium Booking","High Booking")) -> Medium Booking
